{
    "id": "109080890049366669",
    "first_name": "Eda S\u00fcrmeli",
    "last_name": "G\u00fclce",
    "status": "active",
    "current_team_id": "105720640249797517",
    "photo_url": "http://static.lolesports.com/players/1643734200321_silhouette_transparent.png",
    "in_game_name": "Wens",
    "current_team_acronym": "BBL",
    "current_team_name": "BBL Queens",
    "current_league_id": "107019646737643925",
    "current_league_name": "Game Changers EMEA",
    "region": "EMEA",
    "game_records": [
        {
            "platform_game_id": "val:fcfd27d6-d8ac-491e-aaa6-cd68035d0376",
            "game_time": "2024-03-05T16:03:38.708Z",
            "map": "Icebox",
            "agents": {
                "agent_name": "Killjoy"
            },
            "kda": {
                "kills": 23,
                "deaths": 17,
                "assists": 3,
                "combatScore": 6397
            },
            "round_count": 25,
            "gun_kills": {
                "Classic": 3,
                "Vandal": 11,
                "Sheriff": 2,
                "Ghost": 4,
                "Phantom": 3
            },
            "gun_damage": {
                "Classic": 468,
                "Vandal": 1886,
                "Sheriff": 428,
                "": 93,
                "Ghost": 450,
                "Phantom": 488
            }
        },
        {
            "platform_game_id": "val:f2622534-07a0-40af-acb2-51f44cb7098c",
            "game_time": "2024-03-05T17:18:27.575Z",
            "map": "Split",
            "agents": {
                "agent_name": "Cypher"
            },
            "kda": {
                "kills": 17,
                "deaths": 6,
                "assists": 6,
                "combatScore": 4529
            },
            "round_count": 16,
            "gun_kills": {
                "Ghost": 2,
                "Phantom": 14,
                "Classic": 1
            },
            "gun_damage": {
                "Ghost": 362,
                "Phantom": 2722,
                "Classic": 104
            }
        },
        {
            "platform_game_id": "val:9c2218ad-dd8f-4b0f-bbf3-ef19eb58cd54",
            "game_time": "2024-03-05T18:07:08.909Z",
            "map": "Sunset",
            "agents": {
                "agent_name": "Cypher"
            },
            "kda": {
                "kills": 11,
                "deaths": 17,
                "assists": 6,
                "combatScore": 3468
            },
            "round_count": 23,
            "gun_kills": {
                "Ghost": 4,
                "Guardian": 1,
                "Vandal": 1,
                "Phantom": 5
            },
            "gun_damage": {
                "Ghost": 675,
                "Phantom": 1204,
                "Vandal": 240,
                "Sheriff": 110,
                "Guardian": 195,
                "Classic": 26
            }
        },
        {
            "platform_game_id": "val:e6f89ced-f6c8-48a5-94f3-148e94ebe909",
            "game_time": "2024-03-06T16:02:00.708Z",
            "map": "Sunset",
            "agents": {
                "agent_name": "Cypher"
            },
            "kda": {
                "kills": 17,
                "deaths": 15,
                "assists": 2,
                "combatScore": 4613
            },
            "round_count": 20,
            "gun_kills": {
                "Classic": 1,
                "Sheriff": 2,
                "Phantom": 11,
                "Ghost": 2,
                "Vandal": 1
            },
            "gun_damage": {
                "Classic": 260,
                "Sheriff": 464,
                "Phantom": 1823,
                "Ghost": 320,
                "Vandal": 154
            }
        },
        {
            "platform_game_id": "val:13d729bb-073f-4a26-ab3a-d36fec4ff421",
            "game_time": "2024-03-06T17:04:15.915Z",
            "map": "Split",
            "agents": {
                "agent_name": "Cypher"
            },
            "kda": {
                "kills": 11,
                "deaths": 17,
                "assists": 3,
                "combatScore": 3272
            },
            "round_count": 21,
            "gun_kills": {
                "Ghost": 2,
                "Phantom": 8,
                "Sheriff": 1
            },
            "gun_damage": {
                "Ghost": 270,
                "Phantom": 1834,
                "Sheriff": 214,
                "Guardian": 65
            }
        },
        {
            "platform_game_id": "val:ba50f688-89c4-425d-b01b-3b9ec44f304c",
            "game_time": "2024-06-10T18:01:55.789Z",
            "map": "Split",
            "agents": {
                "agent_name": "Cypher"
            },
            "kda": {
                "kills": 21,
                "deaths": 13,
                "assists": 5,
                "combatScore": 6112
            },
            "round_count": 20,
            "gun_kills": {
                "Ghost": 2,
                "Classic": 1,
                "Vandal": 15,
                "Guardian": 1,
                "Sheriff": 2
            },
            "gun_damage": {
                "Ghost": 240,
                "Classic": 156,
                "Vandal": 2778,
                "Guardian": 308,
                "Sheriff": 408
            }
        },
        {
            "platform_game_id": "val:f3cf4ba2-050c-41ac-bbfd-11ee906a1d22",
            "game_time": "2024-06-10T18:57:12.943Z",
            "map": "Lotus",
            "agents": {
                "agent_name": "Viper"
            },
            "kda": {
                "kills": 16,
                "deaths": 12,
                "assists": 5,
                "combatScore": 3892
            },
            "round_count": 20,
            "gun_kills": {
                "Ghost": 3,
                "Bulldog": 1,
                "Vandal": 11,
                "Odin": 1
            },
            "gun_damage": {
                "Ghost": 375,
                "Bulldog": 150,
                "Vandal": 1644,
                "Odin": 349
            }
        },
        {
            "platform_game_id": "val:9021aaba-0af8-44df-be1d-8a6c22020965",
            "game_time": "2024-06-13T17:08:41.948Z",
            "map": "Bind",
            "agents": {
                "agent_name": "Viper"
            },
            "kda": {
                "kills": 20,
                "deaths": 19,
                "assists": 6,
                "combatScore": 5505
            },
            "round_count": 27,
            "gun_kills": {
                "Ghost": 2,
                "Vandal": 17,
                "Sheriff": 1
            },
            "gun_damage": {
                "Ghost": 405,
                "Vandal": 2874,
                "Sheriff": 159
            }
        },
        {
            "platform_game_id": "val:cec17a08-2057-4830-b8ef-8328254b4630",
            "game_time": "2024-06-13T18:16:11.336Z",
            "map": "Ascent",
            "agents": {
                "agent_name": "Killjoy"
            },
            "kda": {
                "kills": 8,
                "deaths": 14,
                "assists": 1,
                "combatScore": 2863
            },
            "round_count": 14,
            "gun_kills": {
                "Vandal": 7,
                "Ghost": 1
            },
            "gun_damage": {
                "Classic": 78,
                "": 36,
                "Vandal": 1193,
                "Bucky": 91,
                "Phantom": 218,
                "Guardian": 56,
                "Ghost": 165
            }
        },
        {
            "platform_game_id": "val:a873f835-34b5-4b43-946a-38c0add32207",
            "game_time": "2024-06-13T18:57:21.674Z",
            "map": "Sunset",
            "agents": {
                "agent_name": "Sage"
            },
            "kda": {
                "kills": 12,
                "deaths": 22,
                "assists": 6,
                "combatScore": 3962
            },
            "round_count": 25,
            "gun_kills": {
                "Classic": 1,
                "Vandal": 10,
                "Sheriff": 1
            },
            "gun_damage": {
                "Classic": 360,
                "Vandal": 2174,
                "Sheriff": 214
            }
        },
        {
            "platform_game_id": "val:537c5377-9382-4595-a3dd-87b2cf1afbea",
            "game_time": "2024-06-14T15:53:24.402Z",
            "map": "Sunset",
            "agents": {
                "agent_name": "Sage"
            },
            "kda": {
                "kills": 12,
                "deaths": 19,
                "assists": 4,
                "combatScore": 3387
            },
            "round_count": 25,
            "gun_kills": {
                "Classic": 2,
                "Vandal": 10
            },
            "gun_damage": {
                "Classic": 156,
                "Guardian": 130,
                "Vandal": 2120
            }
        },
        {
            "platform_game_id": "val:2b65a1c1-c290-4f8a-8ebd-bcaeff108bed",
            "game_time": "2024-06-14T17:05:35.709Z",
            "map": "Bind",
            "agents": {
                "agent_name": "Viper"
            },
            "kda": {
                "kills": 18,
                "deaths": 14,
                "assists": 4,
                "combatScore": 4390
            },
            "round_count": 21,
            "gun_kills": {
                "Vandal": 11,
                "Ghost": 3,
                "Phantom": 4
            },
            "gun_damage": {
                "Vandal": 1729,
                "Sheriff": 55,
                "Ghost": 270,
                "Phantom": 806
            }
        }
    ]
}