{
    "id": "111702980870093748",
    "first_name": "Hugo",
    "last_name": "Santos",
    "status": "active",
    "current_team_id": "111702667590900651",
    "photo_url": "https://s3.us-west-2.amazonaws.com/static.lolesports.com/players/default-headshot.png",
    "in_game_name": "T3mpu",
    "current_team_acronym": "HOF",
    "current_team_name": "HOF Esports",
    "current_league_id": "109551158912464238",
    "current_league_name": "VCT Challengers Portugal",
    "region": "EMEA",
    "game_records": [
        {
            "platform_game_id": "val:42736e3b-91da-4d4e-9ab0-a4c42502a767",
            "game_time": "2024-01-15T23:31:12.083Z",
            "map": "Bind",
            "agents": {
                "agent_name": "Skye"
            },
            "kda": {
                "kills": 25,
                "deaths": 17,
                "assists": 13,
                "combatScore": 6766
            },
            "round_count": 25,
            "gun_kills": {
                "Classic": 1,
                "Vandal": 20,
                "Bulldog": 2,
                "Judge": 2
            },
            "gun_damage": {
                "Classic": 130,
                "Stinger": 112,
                "Vandal": 3454,
                "Spectre": 243,
                "Bulldog": 331,
                "Judge": 212
            }
        },
        {
            "platform_game_id": "val:97ab67ce-14ac-4495-abd8-2bd4d759b498",
            "game_time": "2024-01-16T22:40:29.230Z",
            "map": "Lotus",
            "agents": {
                "agent_name": "Skye"
            },
            "kda": {
                "kills": 2,
                "deaths": 14,
                "assists": 2,
                "combatScore": 841
            },
            "round_count": 13,
            "gun_kills": {
                "Spectre": 2
            },
            "gun_damage": {
                "Vandal": 110,
                "Spectre": 338,
                "Stinger": 81,
                "Classic": 26
            }
        },
        {
            "platform_game_id": "val:c14d2b58-784c-4305-9da5-3de638423490",
            "game_time": "2024-01-22T22:55:10.470Z",
            "map": "Haven",
            "agents": {
                "agent_name": "Skye"
            },
            "kda": {
                "kills": 12,
                "deaths": 16,
                "assists": 4,
                "combatScore": 3538
            },
            "round_count": 20,
            "gun_kills": {
                "Spectre": 2,
                "Phantom": 1,
                "Vandal": 6,
                "Ghost": 2,
                "Guardian": 1
            },
            "gun_damage": {
                "Spectre": 364,
                "Phantom": 156,
                "Vandal": 914,
                "Ghost": 225,
                "Bulldog": 64,
                "Guardian": 325
            }
        },
        {
            "platform_game_id": "val:e816304e-3560-4f2f-a2f2-7165d2e4aed7",
            "game_time": "2024-01-23T19:06:32.553Z",
            "map": "Bind",
            "agents": {
                "agent_name": "Skye"
            },
            "kda": {
                "kills": 4,
                "deaths": 13,
                "assists": 0,
                "combatScore": 1253
            },
            "round_count": 12,
            "gun_kills": {
                "Stinger": 1,
                "Vandal": 2,
                "Phantom": 1
            },
            "gun_damage": {
                "Ghost": 47,
                "Stinger": 175,
                "Vandal": 440,
                "Bulldog": 70,
                "Phantom": 140
            }
        },
        {
            "platform_game_id": "val:eaa7c1de-9270-4d80-a215-8c290a869166",
            "game_time": "2024-01-29T20:01:19.769Z",
            "map": "Lotus",
            "agents": {
                "agent_name": "KAY/O"
            },
            "kda": {
                "kills": 16,
                "deaths": 18,
                "assists": 14,
                "combatScore": 4966
            },
            "round_count": 22,
            "gun_kills": {
                "Ghost": 1,
                "Vandal": 11,
                "Sheriff": 1,
                "Classic": 1,
                "Bulldog": 1,
                "Stinger": 1
            },
            "gun_damage": {
                "Ghost": 105,
                "Vandal": 2382,
                "Sheriff": 214,
                "Classic": 156,
                "Bulldog": 105,
                "Stinger": 94
            }
        },
        {
            "platform_game_id": "val:7ac3a409-15e9-41a3-8905-7c0c3d976bd6",
            "game_time": "2024-01-30T19:03:53.917Z",
            "map": "Lotus",
            "agents": {
                "agent_name": "KAY/O"
            },
            "kda": {
                "kills": 11,
                "deaths": 15,
                "assists": 5,
                "combatScore": 2958
            },
            "round_count": 16,
            "gun_kills": {
                "Classic": 2,
                "Vandal": 6,
                "Sheriff": 1,
                "Phantom": 1
            },
            "gun_damage": {
                "Classic": 234,
                "Vandal": 1080,
                "Sheriff": 159,
                "Phantom": 151
            }
        },
        {
            "platform_game_id": "val:582d2be2-f281-4b09-aeaf-f9118fbab4de",
            "game_time": "2024-02-05T21:15:45.358Z",
            "map": "Lotus",
            "agents": {
                "agent_name": "KAY/O"
            },
            "kda": {
                "kills": 17,
                "deaths": 17,
                "assists": 11,
                "combatScore": 5155
            },
            "round_count": 19,
            "gun_kills": {
                "Classic": 2,
                "Vandal": 3,
                "Phantom": 8,
                "Ghost": 1,
                "Bulldog": 1,
                "Bucky": 1,
                "Guardian": 1
            },
            "gun_damage": {
                "Ghost": 228,
                "Classic": 364,
                "Vandal": 413,
                "Phantom": 1618,
                "Sheriff": 110,
                "Bulldog": 193,
                "Bucky": 20,
                "Guardian": 250
            }
        },
        {
            "platform_game_id": "val:c2995ab9-718c-4e94-9f47-cc7c1b0c1924",
            "game_time": "2024-02-06T22:27:05.385Z",
            "map": "Lotus",
            "agents": {
                "agent_name": "KAY/O"
            },
            "kda": {
                "kills": 15,
                "deaths": 14,
                "assists": 7,
                "combatScore": 4351
            },
            "round_count": 18,
            "gun_kills": {
                "Ghost": 3,
                "Phantom": 3,
                "Vandal": 8,
                "Sheriff": 1
            },
            "gun_damage": {
                "Ghost": 345,
                "Phantom": 547,
                "Vandal": 1481,
                "Stinger": 81,
                "Sheriff": 159,
                "Frenzy": 78
            }
        }
    ]
}